LICENSE
MANIFEST.in
Makefile
README.md
setup.cfg
setup.py
docs/source/conf.py
docs/source/examples.rst
docs/source/index.rst
docs/source/installation.rst
docs/source/introduction.rst
docs/source/tests.rst
easytest/__init__.py
easytest/easytest.py
easytest.egg-info/PKG-INFO
easytest.egg-info/SOURCES.txt
easytest.egg-info/dependency_links.txt
easytest.egg-info/top_level.txt
tests/file.py
tests/test_easy.py
tests/test_easy.py.bak