Metadata-Version: 1.1
Name: easytest
Version: 0.1.5
Summary: easytest - a framework for simple automated testing
Home-page: UNKNOWN
Author: Alexander Loew
Author-email: alexander.loew@lmu.de
License: APACHE 2.0
Keywords: testing,science
Platform: UNKNOWN
Classifier: Programming Language :: Python :: 2.7
